dcor/__init__.py
dcor/_dcor.py
dcor/_dcor_internals.py
dcor/_dcor_internals_numba.py
dcor/_energy.py
dcor/_fast_dcov_avl.py
dcor/_fast_dcov_mergesort.py
dcor/_hypothesis.py
dcor/_partial_dcor.py
dcor/_rowwise.py
dcor/_utils.py
dcor/distances.py
dcor/homogeneity.py
dcor/independence.py
dcor/py.typed
dcor/tests/__init__.py
dcor/tests/test_dcor.py
dcor/tests/test_energy.py
dcor/tests/test_homogeneity.py
dcor/tests/test_independence.py
dcor/tests/test_package.py
dcor/tests/test_rowwise.py
dcor-0.7.dist-info/licenses/LICENSE
dcor-0.7.dist-info/METADATA
dcor-0.7.dist-info/WHEEL
dcor-0.7.dist-info/top_level.txt
dcor-0.7.dist-info/RECORD
