Metadata-Version: 2.4
Name: dcor
Version: 0.7
Summary: dcor: distance correlation and energy statistics in Python.
Author-email: Carlos Ramos Carreño <vnmabus@gmail.com>
Maintainer-email: Carlos Ramos Carreño <vnmabus@gmail.com>
License: MIT License
Project-URL: homepage, https://github.com/vnmabus/dcor
Project-URL: documentation, https://dcor.readthedocs.io
Project-URL: repository, https://github.com/vnmabus/dcor
Keywords: distance correlation,distance covariance,energy distance,e-statistic,dependency measure,homogeneity,independence
Classifier: Development Status :: 4 - Beta
Classifier: Intended Audience :: Developers
Classifier: Intended Audience :: Science/Research
Classifier: License :: OSI Approved :: MIT License
Classifier: Natural Language :: English
Classifier: Operating System :: OS Independent
Classifier: Programming Language :: Python :: 3
Classifier: Programming Language :: Python :: 3.10
Classifier: Programming Language :: Python :: 3.11
Classifier: Programming Language :: Python :: 3.12
Classifier: Topic :: Scientific/Engineering :: Mathematics
Classifier: Topic :: Software Development :: Libraries :: Python Modules
Requires-Python: >=3.10
License-File: LICENSE
Requires-Dist: array-api-compat
Requires-Dist: joblib
Requires-Dist: numba>=0.51
Requires-Dist: numpy
Requires-Dist: scipy
Provides-Extra: docs
Requires-Dist: docutils==0.17.1; extra == "docs"
Requires-Dist: jupyter-sphinx; extra == "docs"
Requires-Dist: matplotlib; extra == "docs"
Requires-Dist: myst-parser; extra == "docs"
Requires-Dist: pygments>=2.4.1; extra == "docs"
Requires-Dist: pandas; extra == "docs"
Requires-Dist: pydata-sphinx-theme; extra == "docs"
Requires-Dist: sphinx>=3; extra == "docs"
Requires-Dist: sphinxcontrib-bibtex; extra == "docs"
Requires-Dist: sphinx-gallery; extra == "docs"
Provides-Extra: test
Requires-Dist: array-api-strict; extra == "test"
Requires-Dist: numpy<2; extra == "test"
Requires-Dist: pytest; extra == "test"
Requires-Dist: pytest-cov; extra == "test"
Requires-Dist: pytest-subtests; extra == "test"
Dynamic: license-file
